pymodaq_plugins_pylablib_camera/VERSION
pymodaq_plugins_pylablib_camera/__init__.py
pymodaq_plugins_pylablib_camera/daq_move_plugins/__init__.py
pymodaq_plugins_pylablib_camera/daq_viewer_plugins/__init__.py
pymodaq_plugins_pylablib_camera/daq_viewer_plugins/plugins_0D/__init__.py
pymodaq_plugins_pylablib_camera/daq_viewer_plugins/plugins_1D/__init__.py
pymodaq_plugins_pylablib_camera/daq_viewer_plugins/plugins_2D/__init__.py
pymodaq_plugins_pylablib_camera/daq_viewer_plugins/plugins_2D/daq_2Dviewer_AndorPLL.py
pymodaq_plugins_pylablib_camera/daq_viewer_plugins/plugins_2D/daq_2Dviewer_GenericPylablibCamera.py
pymodaq_plugins_pylablib_camera/daq_viewer_plugins/plugins_2D/daq_2Dviewer_PCOPLL.py
pymodaq_plugins_pylablib_camera/daq_viewer_plugins/plugins_2D/daq_2Dviewer_ThorlabsPLL.py
pymodaq_plugins_pylablib_camera/daq_viewer_plugins/plugins_ND/__init__.py
pymodaq_plugins_pylablib_camera/extension/__init__.py
pymodaq_plugins_pylablib_camera/hardware/__init__.py
pymodaq_plugins_pylablib_camera/models/__init__.py
pymodaq_plugins_pylablib_camera-1.0.1.dist-info/LICENSE
pymodaq_plugins_pylablib_camera-1.0.1.dist-info/METADATA
pymodaq_plugins_pylablib_camera-1.0.1.dist-info/WHEEL
pymodaq_plugins_pylablib_camera-1.0.1.dist-info/entry_points.txt
pymodaq_plugins_pylablib_camera-1.0.1.dist-info/top_level.txt
pymodaq_plugins_pylablib_camera-1.0.1.dist-info/RECORD
