Metadata-Version: 2.1
Name: pymodaq_plugins_pylablib_camera
Version: 1.0.1
Summary: Generic pymodaq plugins based on the pylablib library 
Home-page: https://github.com/Attolab/pymodaq_plugins_pylablib
Author: Romain Géneaux
Author-email: romain.geneaux@cea.fr
License: MIT
Classifier: Programming Language :: Python :: 3
Classifier: Development Status :: 5 - Production/Stable
Classifier: Environment :: Other Environment
Classifier: Intended Audience :: Science/Research
Classifier: Topic :: Scientific/Engineering :: Human Machine Interfaces
Classifier: Topic :: Scientific/Engineering :: Visualization
Classifier: License :: CeCILL-B Free Software License Agreement (CECILL-B)
Classifier: Operating System :: OS Independent
Classifier: Topic :: Software Development :: Libraries :: Python Modules
Classifier: Topic :: Software Development :: User Interfaces
License-File: LICENSE
Requires-Dist: toml
Requires-Dist: numpy
Requires-Dist: pymodaq>4.0
Requires-Dist: pylablib
